tx_extension_clip/__init__.py
tx_extension_clip/config.py
tx_extension_clip/hasher.py
tx_extension_clip/index.py
tx_extension_clip/manifest.py
tx_extension_clip/matcher.py
tx_extension_clip/signal.py
tx_extension_clip/utils/__init__.py
tx_extension_clip/utils/distance.py
tx_extension_clip/utils/uint.py
tx_extension_clip-0.2.5.dist-info/METADATA
tx_extension_clip-0.2.5.dist-info/WHEEL
tx_extension_clip-0.2.5.dist-info/top_level.txt
tx_extension_clip-0.2.5.dist-info/RECORD
